trading/__init__.py
trading/data/__init__.py
trading/data/client.py
trading/data/constants.py
trading/models/__init__.py
trading/models/backtester.py
trading/models/broker.py
trading/models/contract.py
trading/models/forex.py
trading/models/margin.py
trading/models/market_data.py
trading/models/market_impact.py
trading/utils/__init__.py
trading/utils/dates.py
trading/v2/__init__.py
trading/v2/backtest_engine.py
trading/v2/portfolio_env.py
trading/v2/trading_env.py
trading/v2/account/__init__.py
trading/v2/account/account_event.py
trading/v2/account/account_manager.py
trading/v2/brokerage/__init__.py
trading/v2/brokerage/backtest_brokerage.py
trading/v2/brokerage/brokerage_base.py
trading/v2/brokerage/ib_brokerage.py
trading/v2/data/__init__.py
trading/v2/data/backtest_data_feed.py
trading/v2/data/bar_event.py
trading/v2/data/data_board.py
trading/v2/data/data_feed_base.py
trading/v2/data/live_data_feed.py
trading/v2/data/tick_event.py
trading/v2/event/__init__.py
trading/v2/event/backtest_event_engine.py
trading/v2/event/event.py
trading/v2/event/live_event_engine.py
trading/v2/log/__init__.py
trading/v2/log/tick_recorder.py
trading/v2/log/trade_recorder.py
trading/v2/log/trade_recorder_base.py
trading/v2/order/__init__.py
trading/v2/order/fill_event.py
trading/v2/order/order_event.py
trading/v2/order/order_flag.py
trading/v2/order/order_manager.py
trading/v2/order/order_status.py
trading/v2/order/order_type.py
trading/v2/performance/__init__.py
trading/v2/performance/performance_manager.py
trading/v2/performance/report_manager.py
trading/v2/position/__init__.py
trading/v2/position/contract_event.py
trading/v2/position/position.py
trading/v2/position/position_event.py
trading/v2/position/position_manager.py
trading/v2/risk/__init__.py
trading/v2/risk/margin_manager.py
trading/v2/risk/risk_manager.py
trading/v2/risk/risk_manager_base.py
trading/v2/strategy/__init__.py
trading/v2/strategy/strategy_base.py
trading/v2/strategy/strategy_manager.py
systematic_trading-0.0.13.dist-info/LICENSE
systematic_trading-0.0.13.dist-info/METADATA
systematic_trading-0.0.13.dist-info/WHEEL
systematic_trading-0.0.13.dist-info/top_level.txt
systematic_trading-0.0.13.dist-info/RECORD
